fenci/__init__.py
fenci/base.py
fenci/const.py
fenci/dict_small.txt
fenci/hmm_data.json
fenci/hmm_segment.py
fenci/nltk_utils.py
fenci/segment.py
fenci/train_hmm.py
fenci/utils.py
fenci-0.3.4.dist-info/licenses/LICENSE
fenci-0.3.4.dist-info/METADATA
fenci-0.3.4.dist-info/WHEEL
fenci-0.3.4.dist-info/top_level.txt
fenci-0.3.4.dist-info/RECORD
