Metadata-Version: 2.4
Name: fenci
Version: 0.3.4
Summary: 中文分词
Home-page: https://github.com/a358003542/fenci
Author: wanze
Author-email: a358003542@outlook.com
Maintainer: wanze
Maintainer-email: a358003542@outlook.com
License: MIT
Keywords: word_segment,nlp
Platform: Linux
Platform: windows
Classifier: Operating System :: Microsoft
Classifier: Operating System :: POSIX :: Linux
Classifier: Programming Language :: Python :: 3
Classifier: Topic :: Text Processing
License-File: LICENSE
Requires-Dist: filelock
Dynamic: author
Dynamic: author-email
Dynamic: classifier
Dynamic: description
Dynamic: description-content-type
Dynamic: home-page
Dynamic: keywords
Dynamic: license
Dynamic: license-file
Dynamic: maintainer
Dynamic: maintainer-email
Dynamic: platform
Dynamic: requires-dist
Dynamic: summary
